{
  "vowels": "aeiouy",
  "payload_map": {
    "a": {"type": "base_type", "tag": "base", "principle": "aperture/origin"},
    "e": {"type": "encompass", "tag": "relate", "principle": "reflexive-relational"},
    "i": {"type": "identify", "tag": "index", "principle": "minimal unit/index"},
    "o": {"type": "whole", "tag": "object", "principle": "wholeness/container"},
    "u": {"type": "union", "tag": "capacity", "principle": "root/union/channel"},
    "y": {"type": "branch", "tag": "branch", "principle": "bifurcated value"}
  },
  "operator_map": {
    "b": "bind",
    "c": "contain",
    "d": "decide",
    "f": "flow",
    "g": "grasp",
    "h": "animate",
    "j": "project",
    "k": "clamp",
    "l": "align",
    "m": "multiply",
    "n": "negate",
    "p": "present",
    "q": "query",
    "r": "rotate",
    "s": "stream",
    "t": "instantiate",
    "v": "vector",
    "w": "web",
    "x": "cross",
    "z": "quantize"
  },
  "cluster_map": {
    "st": ["stream", "instantiate"],
    "tr": ["instantiate", "rotate"],
    "pl": ["present", "align"],
    "str": ["stream", "instantiate", "rotate"],
    "spr": ["stream", "present", "rotate"],
    "sk": ["stream", "clamp"],
    "sc": ["stream", "clamp"]
  },
  "enhanced_cluster_map": {
    "st": {"ops": ["stream", "instantiate"], "gloss": "flow→point", "confidence": 0.90},
    "tr": {"ops": ["instantiate", "rotate"], "gloss": "structure→rotate", "confidence": 0.85},
    "pl": {"ops": ["present", "align"], "gloss": "present→align", "confidence": 0.80},
    "str": {"ops": ["stream", "instantiate", "rotate"], "gloss": "flow→pin→stabilize", "confidence": 0.85},
    "spr": {"ops": ["stream", "present", "rotate"], "gloss": "flow→emerge→distribute", "confidence": 0.80},
    "sk": {"ops": ["stream", "clamp"], "gloss": "scan→select", "confidence": 0.95},
    "sc": {"ops": ["stream", "clamp"], "gloss": "scan→select (variant)", "confidence": 0.90},
    "gr": {"ops": ["grasp", "rotate"], "gloss": "grab→turn", "confidence": 0.85},
    "br": {"ops": ["bind", "rotate"], "gloss": "bind→revolve", "confidence": 0.80},
    "cr": {"ops": ["contain", "rotate"], "gloss": "encircle", "confidence": 0.80},
    "dr": {"ops": ["decide", "rotate"], "gloss": "determine→direction", "confidence": 0.75},
    "fr": {"ops": ["flow", "rotate"], "gloss": "fluid→rotation", "confidence": 0.80},
    "pr": {"ops": ["present", "rotate"], "gloss": "present→rotation", "confidence": 0.75},
    "ld": {"ops": ["align", "decide"], "gloss": "align→decide (modal)", "confidence": 0.70},
    "ght": {"ops": ["grasp", "animate", "instantiate"], "gloss": "grasp→breathe→pin", "confidence": 0.65},
    "th": {"ops": ["instantiate", "animate"], "gloss": "pin→breathe (abstract)", "confidence": 0.85},
    "wh": {"ops": ["web", "animate"], "gloss": "web→breathe (query)", "confidence": 0.75},
    "ch": {"ops": ["contain", "animate"], "gloss": "contain→breathe (check)", "confidence": 0.70},
    "sh": {"ops": ["stream", "animate"], "gloss": "stream→breathe (smooth)", "confidence": 0.75}
  },
  "complete_operator_map": {
    "b": {"op": "bind", "principle": "boundary/bulge left", "confidence": 0.85},
    "d": {"op": "decide", "principle": "delineate/door right", "confidence": 0.85},
    "g": {"op": "grasp", "principle": "gate/gather return", "confidence": 0.85},
    "k": {"op": "clamp", "principle": "cut/classify branch", "confidence": 0.95},
    "m": {"op": "multiply", "principle": "matrix/mass accumulate", "confidence": 0.95},
    "s": {"op": "stream", "principle": "scan/scatter flow", "confidence": 0.95},
    "t": {"op": "instantiate", "principle": "terminal/tool pin", "confidence": 0.95},
    "c": {"op": "contain", "principle": "curve/gather approach", "confidence": 0.90},
    "f": {"op": "flow", "principle": "fork/friction split", "confidence": 0.90},
    "h": {"op": "animate", "principle": "breath/aspiration", "confidence": 0.80},
    "j": {"op": "project", "principle": "jet/joint trajectory", "confidence": 0.75},
    "l": {"op": "align", "principle": "line/level lateral", "confidence": 0.90},
    "n": {"op": "negate", "principle": "next/not alternative", "confidence": 0.85},
    "p": {"op": "present", "principle": "press/project emerge", "confidence": 0.80},
    "q": {"op": "query", "principle": "query outlet from whole", "confidence": 0.85},
    "r": {"op": "rotate", "principle": "route/recur vibration", "confidence": 0.90},
    "v": {"op": "vector", "principle": "vector/channel directed", "confidence": 0.85},
    "w": {"op": "web", "principle": "wave/web dual channels", "confidence": 0.90},
    "x": {"op": "cross", "principle": "nexus intersection", "confidence": 0.85},
    "y": {"op": "branch", "principle": "bifurcated split/choice", "confidence": 0.80},
    "z": {"op": "quantize", "principle": "zip/signal discretize", "confidence": 0.75}
  },
  "typed_payload_map": {
    "a": {"type": "base_type", "tag": "base", "principle": "aperture/origin", "confidence": 0.95},
    "e": {"type": "relation", "tag": "relational", "principle": "reflexive-relational", "confidence": 0.90},
    "i": {"type": "index", "tag": "index", "principle": "minimal unit", "confidence": 0.95},
    "o": {"type": "container", "tag": "object", "principle": "wholeness", "confidence": 0.90},
    "u": {"type": "struct", "tag": "capacity", "principle": "root/union", "confidence": 0.85},
    "y": {"type": "branch", "tag": "branch", "principle": "bifurcated", "confidence": 0.80}
  }
}
